setup.py
src/ua2/__init__.py
src/ua2.djfab.egg-info/PKG-INFO
src/ua2.djfab.egg-info/SOURCES.txt
src/ua2.djfab.egg-info/dependency_links.txt
src/ua2.djfab.egg-info/eager_resources.txt
src/ua2.djfab.egg-info/namespace_packages.txt
src/ua2.djfab.egg-info/not-zip-safe
src/ua2.djfab.egg-info/top_level.txt
src/ua2/djfab/__init__.py
src/ua2/djfab/common.py