Metadata-Version: 1.0
Name: ua2.djfab
Version: 0.0.4
Summary: Generic fabric commands for all django projects
Home-page: https://bitbucket.org/ua2web/ua2.djfab
Author: avkoval
Author-email: alex@ua2web.com
License: BSD License
Platform: UNKNOWN
